[
    {
        "l_barcode": "P21-10704-AG",
        "redcap_event_name": "laboratory_arm_1",
        "identification_complete": "2",
        "h_datetime": "2024-02-27 11:03",
        "mpv": "12.0",
        "mpv_unit": "fL",
        "hgb": "10.3",
        "hgb_unit": "g/dL",
        "plcr": "47.4",
        "plcr_unit": "%",
        "mono_count": "0.36",
        "mono_count_unit": "x10^3/\u00b5L",
        "pct": "0.01",
        "pct_unit": "%",
        "neut_count": "2.41",
        "neut_count_unit": "x10^3/\u00b5L",
        "ig_percent": "1.2",
        "ig_percent_unit": "%",
        "wbc": "4.20",
        "wbc_unit": "x10^3/\u00b5L",
        "hct": "28.7",
        "hct_unit": "%",
        "lymph_count": "1.42",
        "lymph_count_unit": "x10^3/\u00b5L",
        "mchc": "35.9",
        "mchc_unit": "g/dL",
        "mcv": "85.9",
        "mcv_unit": "fL",
        "plt": "7",
        "plt_unit": "x10^3/\u00b5L",
        "baso_count": "0.01",
        "baso_count_unit": "x10^3/\u00b5L",
        "eo_count": "0.00",
        "eo_count_unit": "x10^3/\u00b5L",
        "rbc": "3.34",
        "rbc_unit": "x10^6/\u00b5L",
        "neut_percent": "57.4",
        "neut_percent_unit": "%",
        "micror_percent": "2.5",
        "micror_percent_unit": "%",
        "rdwcv": "12.5",
        "rdwcv_unit": "%",
        "lymph_percent": "33.8",
        "lymph_percent_unit": "%",
        "mono_percent": "8.6",
        "mono_percent_unit": "%",
        "mch": "30.8",
        "mch_unit": "pg",
        "eo_percent": "0.0",
        "eo_percent_unit": "%",
        "baso_percent": "0.2",
        "baso_percent_unit": "%",
        "rdwsd": "38.5",
        "rdwsd_unit": "fL",
        "ig_count": "0.05",
        "ig_count_unit": "x10^3/\u00b5L",
        "pdw": "6.0",
        "pdw_unit": "fL",
        "macror_percent": "3.8",
        "macror_percent_unit": "%",
        "haematology_complete": "2"
    }
]